vanoma_api_utils/__init__.py
vanoma_api_utils/admin_api.py
vanoma_api_utils/auth_api.py
vanoma_api_utils/communication_api.py
vanoma_api_utils/constants.py
vanoma_api_utils/django/__init__.py
vanoma_api_utils/django/fields.py
vanoma_api_utils/django/functions.py
vanoma_api_utils/django/middlewares.py
vanoma_api_utils/django/request.py
vanoma_api_utils/django/settings.py
vanoma_api_utils/django/tests.py
vanoma_api_utils/django/validators.py
vanoma_api_utils/django/views.py
vanoma_api_utils/exceptions.py
vanoma_api_utils/http.py
vanoma_api_utils/jwt.py
vanoma_api_utils/mini_huey/__init__.py
vanoma_api_utils/mini_huey/apps.py
vanoma_api_utils/misc.py
vanoma_api_utils/phone_numbers.py
vanoma_api_utils/py.typed
vanoma_api_utils/request.py
vanoma_api_utils/rest_framework/__init__.py
vanoma_api_utils/rest_framework/exceptions.py
vanoma_api_utils/rest_framework/filters.py
vanoma_api_utils/rest_framework/generics.py
vanoma_api_utils/rest_framework/pagination.py
vanoma_api_utils/rest_framework/parsers.py
vanoma_api_utils/rest_framework/renderers.py
vanoma_api_utils/rest_framework/responses.py
vanoma_api_utils/rest_framework/serializers.py
vanoma_api_utils/rest_framework/tests.py
vanoma_api_utils/rest_framework/views.py
vanoma_api_utils/rest_framework/viewsets.py
vanoma_api_utils/sentry.py
vanoma_api_utils/tests.py
vanoma_api_utils-0.121.0.dist-info/METADATA
vanoma_api_utils-0.121.0.dist-info/WHEEL
vanoma_api_utils-0.121.0.dist-info/RECORD
