Metadata-Version: 2.1
Name: vanoma-api-utils
Version: 0.121.0
Summary: Python utils for vanoma APIs
Author: Vanoma
Author-email: contact@vanoma.com
Requires-Python: >=3.8,<4.0
Classifier: Programming Language :: Python :: 3
Classifier: Programming Language :: Python :: 3.8
Classifier: Programming Language :: Python :: 3.9
Classifier: Programming Language :: Python :: 3.10
Classifier: Programming Language :: Python :: 3.11
Requires-Dist: Faker (>=9.9.1,<10.0.0)
Requires-Dist: PyJWT (>=2.3.0,<3.0.0)
Requires-Dist: babel (>=2.12.1,<3.0.0)
Requires-Dist: boto3 (>=1.24.89,<2.0.0)
Requires-Dist: dj-database-url (>=0.5.0,<0.6.0)
Requires-Dist: django (>=4.2,<5.0)
Requires-Dist: django-filter (>=21.1,<22.0)
Requires-Dist: django-storages (>=1.13.1,<2.0.0)
Requires-Dist: djangorestframework (>=3.14.0,<4.0.0)
Requires-Dist: djangorestframework-camel-case (>=1.2.0,<2.0.0)
Requires-Dist: drf-extra-fields (>=3.4.1,<4.0.0)
Requires-Dist: drf-flex-fields (>=1.0.2,<2.0.0)
Requires-Dist: huey (>=2.4.5,<3.0.0)
Requires-Dist: mutagen (>=1.46.0,<2.0.0)
Requires-Dist: phonenumbers (>=8.12.37,<9.0.0)
Requires-Dist: pillow (>=9.4.0,<10.0.0)
Requires-Dist: psycopg2 (>=2.9.3,<3.0.0)
Requires-Dist: pyhumps (>=3.5.3,<4.0.0)
Requires-Dist: python-dateutil (>=2.8.2,<3.0.0)
Requires-Dist: requests (>=2.27.1,<3.0.0)
Requires-Dist: sentry-sdk (>=1.12.1,<2.0.0)
Requires-Dist: shortuuid (>=1.0.9,<2.0.0)
